FragenAntwortLLMGPU/__init__.py
FragenAntwortLLMGPU/document_processor.py
fragenantwortllmgpu-0.1.12.dist-info/licenses/LICENSE
fragenantwortllmgpu-0.1.12.dist-info/METADATA
fragenantwortllmgpu-0.1.12.dist-info/WHEEL
fragenantwortllmgpu-0.1.12.dist-info/entry_points.txt
fragenantwortllmgpu-0.1.12.dist-info/top_level.txt
fragenantwortllmgpu-0.1.12.dist-info/RECORD
