Metadata-Version: 2.4
Name: FragenAntwortLLMGPU
Version: 0.1.12
Summary: A package for processing documents and generating questions and answers using LLMs on GPU and CPU.
Author: Mehrdad Almasi, Demival Vasques, and Lars Wieneke
Classifier: Programming Language :: Python :: 3
Classifier: License :: OSI Approved :: MIT License
Classifier: Operating System :: OS Independent
Requires-Python: >=3.9
License-File: LICENSE
Requires-Dist: PyMuPDF
Requires-Dist: tokenizers
Requires-Dist: semantic-text-splitter==0.13.3
Requires-Dist: langchain
Requires-Dist: langchain_community
Requires-Dist: torchvision
Requires-Dist: torchaudio
Requires-Dist: ctransformers
Requires-Dist: transformers>=4.37.0
Dynamic: author
Dynamic: classifier
Dynamic: description
Dynamic: description-content-type
Dynamic: license-file
Dynamic: requires-dist
Dynamic: requires-python
Dynamic: summary
